[null,{"name":"zgłoś","permissions":"NONE","restriction":"1","actions":[{"condition":"1","comparison":"0","value":"1","iftrue":"3","iftrueVal":"4","iffalse":"0","iffalseVal":"","name":"Check Parameters"},{"title":"","author":"","color":"","timestamp":"false","url":"","authorIcon":"","imageUrl":"","thumbUrl":"","storage":"1","varName":"embediro_ERROR1","name":"Create Embed Message"},{"storage":"1","varName":"embediro_ERROR1","message":"Oznacz osobę którą chcesz zgłosić!","name":"Set Embed Description"},{"storage":"1","varName":"embediro_ERROR1","channel":"0","varName2":"","name":"Send Embed Message"},{"name":"End Action Sequence"},{"condition":"0","comparison":"2","value":"0","iftrue":"3","iftrueVal":"4","iffalse":"0","iffalseVal":"","name":"Check Parameters"},{"title":"","author":"","color":"","timestamp":"false","url":"","authorIcon":"","imageUrl":"","thumbUrl":"","storage":"1","varName":"embediro_ERROR2","name":"Create Embed Message"},{"storage":"1","varName":"embediro_ERROR2","message":"Podaj powód zgłoszenia!","name":"Set Embed Description"},{"storage":"1","varName":"embediro_ERROR2","channel":"0","varName2":"","name":"Send Embed Message"},{"name":"End Action Sequence"},{"storage":"0","varName":"","name":"Delete Message"},{"info":"2","infoIndex":"1","storage":"1","varName":"user","name":"Store Command Params"},{"info":"1","infoIndex":"2","storage":"1","varName":"reason","name":"Store Command Params"},{"info":"1","find":"「😡」zgłoszenia","storage":"1","varName":"zgloszenia","name":"Find Channel"},{"member":"0","varName":"","info":"1","storage":"1","varName2":"id","name":"Store Member Info"},{"member":"1","varName":"","info":"2","storage":"1","varName2":"user_dodaje","name":"Store Member Info"},{"member":"1","varName":"","info":"16","storage":"1","varName2":"AVATAR_ZGLASZAJACEGO","name":"Store Member Info"},{"member":"0","varName":"","info":"16","storage":"1","varName2":"AVATAR_TYPA","name":"Store Member Info"},{"title":"","author":"Dodano nowe zgłoszenie!","color":"#E60EF1","timestamp":"false","url":"","authorIcon":"${tempVars(\"AVATAR_ZGLASZAJACEGO\")}","imageUrl":"","thumbUrl":"${tempVars(\"AVATAR_TYPA\")}","storage":"1","varName":"reported4","name":"Create Embed Message"},{"storage":"1","varName":"reported4","message":"- Zgłaszający: **${tempVars(\"user_dodaje\")}**\n- Zgłoszona osoba: **${tempVars(\"user\")}**\n- Powód zgłoszenia: **${tempVars(\"reason\")}**","name":"Set Embed Description"},{"storage":"1","varName":"reported4","channel":"5","varName2":"zgloszenia","name":"Send Embed Message"},{"channel":"0","varName":"","message":"**Dziękujemy!** Twoje zgłoszenie zostało wysłane do naszego zarządu.","storage":"1","varName2":"send","name":"Send Message"},{"channel":"3","varName":"zgloszenia","info":"4","storage":"1","varName2":"lastmsg","name":"Store Channel Info"},{"time":"5","measurement":"1","name":"Wait"},{"storage":"1","varName":"send","name":"Delete Message"}]},{"name":"clear","permissions":"MANAGE_MESSAGES","restriction":"1","actions":[{"info":"0","infoIndex":"1","storage":"1","varName":"clear","name":"Store Command Params"},{"channel":"0","count":"${tempVars(\"clear\")}","condition":"0","custom":"","varName":"","name":"Delete Bulk Messages"},{"channel":"0","varName":"","message":"**Chat zostal wyczyszczony**","storage":"1","varName2":"czysc","name":"Send Message"},{"storage":"0","varName":"","name":"Delete Message"},{"time":"2","measurement":"1","name":"Wait"},{"storage":"1","varName":"czysc","name":"Delete Message"}]},{"name":"ogłoszenie","permissions":"ADMINISTRATOR","restriction":"1","actions":[{"condition":"0","comparison":"2","value":"0","iftrue":"3","iftrueVal":"4","iffalse":"0","iffalseVal":"","name":"Check Parameters"},{"title":"","author":"","color":"","timestamp":"false","url":"","authorIcon":"","imageUrl":"","thumbUrl":"","storage":"1","varName":"embediro_ERROR2","name":"Create Embed Message"},{"storage":"1","varName":"embediro_ERROR2","message":"Podaj treść ogłoszenia","name":"Set Embed Description"},{"storage":"1","varName":"embediro_ERROR2","channel":"0","varName2":"","name":"Send Embed Message"},{"name":"End Action Sequence"},{"storage":"0","varName":"","name":"Delete Message"},{"info":"1","infoIndex":"1","storage":"1","varName":"reason","name":"Store Command Params"},{"info":"1","find":"「📣」ogłoszenia","storage":"1","varName":"zgloszenia","name":"Find Channel"},{"member":"0","varName":"","info":"1","storage":"1","varName2":"id","name":"Store Member Info"},{"member":"1","varName":"","info":"2","storage":"1","varName2":"user_dodaje","name":"Store Member Info"},{"member":"1","varName":"","info":"16","storage":"1","varName2":"AVATAR_ZGLASZAJACEGO","name":"Store Member Info"},{"title":"Ogłoszenie:","author":"","color":"#00FF00","timestamp":"false","url":"","authorIcon":"","imageUrl":"","thumbUrl":"","storage":"1","varName":"reported4","name":"Create Embed Message"},{"storage":"1","varName":"reported4","message":"${tempVars(\"reason\")}","name":"Set Embed Description"},{"storage":"1","varName":"reported4","channel":"5","varName2":"zgloszenia","name":"Send Embed Message"},{"channel":"0","varName":"","message":"Twoje ogłoszenie zostało wysłane","storage":"1","varName2":"send","name":"Send Message"},{"channel":"3","varName":"zgloszenia","info":"4","storage":"1","varName2":"lastmsg","name":"Store Channel Info"},{"time":"5","measurement":"1","name":"Wait"},{"storage":"1","varName":"send","name":"Delete Message"}]},{"name":"p1","permissions":"ADMINISTRATOR","restriction":"1","actions":[{"condition":"0","comparison":"2","value":"0","iftrue":"3","iftrueVal":"4","iffalse":"0","iffalseVal":"","name":"Check Parameters"},{"title":"","author":"","color":"","timestamp":"false","url":"","authorIcon":"","imageUrl":"","thumbUrl":"","storage":"1","varName":"embediro_ERROR2","name":"Create Embed Message"},{"storage":"1","varName":"embediro_ERROR2","message":"Podaj treść ogłoszenia","name":"Set Embed Description"},{"storage":"1","varName":"embediro_ERROR2","channel":"0","varName2":"","name":"Send Embed Message"},{"name":"End Action Sequence"},{"storage":"0","varName":"","name":"Delete Message"},{"info":"1","infoIndex":"1","storage":"1","varName":"reason","name":"Store Command Params"},{"info":"1","find":"「📕」zarząd","storage":"1","varName":"zgloszenia","name":"Find Channel"},{"member":"0","varName":"","info":"1","storage":"1","varName2":"id","name":"Store Member Info"},{"member":"1","varName":"","info":"2","storage":"1","varName2":"user_dodaje","name":"Store Member Info"},{"member":"1","varName":"","info":"16","storage":"1","varName2":"AVATAR_ZGLASZAJACEGO","name":"Store Member Info"},{"title":"Pomoc:","author":"","color":"#00FF00","timestamp":"false","url":"","authorIcon":"","imageUrl":"","thumbUrl":"","storage":"1","varName":"reported4","name":"Create Embed Message"},{"storage":"1","varName":"reported4","message":"- Treść pomocy: **${tempVars(\"reason\")}**\n- Zgłaszający: **${tempVars(\"user_dodaje\")}**\n","name":"Set Embed Description"},{"storage":"1","varName":"reported4","channel":"5","varName2":"zgloszenia","name":"Send Embed Message"},{"channel":"0","varName":"","message":"Twoje ogłoszenie zostało wysłane","storage":"1","varName2":"send","name":"Send Message"},{"channel":"3","varName":"zgloszenia","info":"4","storage":"1","varName2":"lastmsg","name":"Store Channel Info"},{"time":"5","measurement":"1","name":"Wait"},{"storage":"1","varName":"send","name":"Delete Message"}]},{"name":"p2","permissions":"ADMINISTRATOR","restriction":"1","actions":[{"condition":"0","comparison":"2","value":"0","iftrue":"3","iftrueVal":"4","iffalse":"0","iffalseVal":"","name":"Check Parameters"},{"title":"","author":"","color":"","timestamp":"false","url":"","authorIcon":"","imageUrl":"","thumbUrl":"","storage":"1","varName":"embediro_ERROR2","name":"Create Embed Message"},{"storage":"1","varName":"embediro_ERROR2","message":"Podaj treść ogłoszenia","name":"Set Embed Description"},{"storage":"1","varName":"embediro_ERROR2","channel":"0","varName2":"","name":"Send Embed Message"},{"name":"End Action Sequence"},{"storage":"0","varName":"","name":"Delete Message"},{"info":"1","infoIndex":"1","storage":"1","varName":"reason","name":"Store Command Params"},{"channelName":"Pomoc","topic":"","position":"「🤪」4fun i reszta","storage":"1","varName":"kanał","name":"Create Text Channel"},{"info":"1","find":"「📕」zarząd","storage":"1","varName":"zgloszenia","name":"Find Channel"},{"member":"0","varName":"","info":"1","storage":"1","varName2":"id","name":"Store Member Info"},{"member":"1","varName":"","info":"2","storage":"1","varName2":"user_dodaje","name":"Store Member Info"},{"member":"1","varName":"","info":"16","storage":"1","varName2":"AVATAR_ZGLASZAJACEGO","name":"Store Member Info"},{"info":"1","find":"Ping: Zarząd","storage":"1","varName":"Zarząd","name":"Find Role"},{"info":"1","find":"Ping: Ekipa","storage":"1","varName":"Ekipa","name":"Find Role"},{"title":"Pomoc:","author":"","color":"#00FF00","timestamp":"false","url":"","authorIcon":"","imageUrl":"","thumbUrl":"","storage":"1","varName":"reported4","name":"Create Embed Message"},{"storage":"1","varName":"reported4","message":"Treść pomocy: **${tempVars(\"reason\")}**\nPingi dla: **${tempVars(\"Zarząd\")}** **${tempVars(\"Ekipa\")}**\n***Aby zamknąć pomoc użyj komedy:*** */pomoc_zamknij*\n","name":"Set Embed Description"},{"storage":"1","varName":"reported4","channel":"5","varName2":"zgloszenia","name":"Send Embed Message"},{"channel":"0","varName":"","message":"Twoje ogłoszenie zostało wysłane","storage":"1","varName2":"send","name":"Send Message"},{"channel":"3","varName":"zgloszenia","info":"4","storage":"1","varName2":"lastmsg","name":"Store Channel Info"},{"time":"5","measurement":"1","name":"Wait"},{"storage":"1","varName":"send","name":"Delete Message"}]},{"name":"p3","permissions":"ADMINISTRATOR","restriction":"1","actions":[{"condition":"0","comparison":"2","value":"0","iftrue":"3","iftrueVal":"4","iffalse":"0","iffalseVal":"","name":"Check Parameters"},{"title":"","author":"","color":"","timestamp":"false","url":"","authorIcon":"","imageUrl":"","thumbUrl":"","storage":"1","varName":"embediro_ERROR2","name":"Create Embed Message"},{"storage":"1","varName":"embediro_ERROR2","message":"Podaj treść ogłoszenia","name":"Set Embed Description"},{"storage":"1","varName":"embediro_ERROR2","channel":"0","varName2":"","name":"Send Embed Message"},{"name":"End Action Sequence"},{"storage":"0","varName":"","name":"Delete Message"},{"info":"1","infoIndex":"1","storage":"1","varName":"reason","name":"Store Command Params"},{"info":"1","find":"「📕」zarząd","storage":"1","varName":"zgloszenia","name":"Find Channel"},{"member":"0","varName":"","info":"1","storage":"1","varName2":"id","name":"Store Member Info"},{"member":"1","varName":"","info":"2","storage":"1","varName2":"user_dodaje","name":"Store Member Info"},{"member":"1","varName":"","info":"16","storage":"1","varName2":"AVATAR_ZGLASZAJACEGO","name":"Store Member Info"},{"title":"Pomoc:","author":"","color":"#00FF00","timestamp":"false","url":"","authorIcon":"","imageUrl":"","thumbUrl":"","storage":"1","varName":"reported4","name":"Create Embed Message"},{"info":"1","find":"Ping: Zarząd","storage":"1","varName":"Zarząd","name":"Find Role"},{"info":"1","find":"Ping: Ekipa","storage":"1","varName":"Ekipa","name":"Find Role"},{"storage":"1","varName":"reported4","message":"Treść pomocy: **${tempVars(\"reason\")}**\nPingi dla: **${tempVars(\"Zarząd\")}** **${tempVars(\"Ekipa\")}**\n***Aby zamknąć pomoc użyj komedy:*** */pomoc_zamknij*\n","name":"Set Embed Description"},{"storage":"1","varName":"reported4","channel":"5","varName2":"zgloszenia","name":"Send Embed Message"},{"channel":"0","varName":"","message":"Twoje ogłoszenie zostało wysłane","storage":"1","varName2":"send","name":"Send Message"},{"channel":"3","varName":"zgloszenia","info":"4","storage":"1","varName2":"lastmsg","name":"Store Channel Info"},{"time":"5","measurement":"1","name":"Wait"},{"storage":"1","varName":"send","name":"Delete Message"}]},{"name":"mute","permissions":"MUTE_MEMBERS","restriction":"1","actions":[{"info":"1","find":"🔇Wyciszony🔇","storage":"1","varName":"mute","name":"Find Role"},{"member":"0","varName2":"","role":"3","varName":"mute","name":"Add Member Role"},{"info":"1","find":"🎮Gracz🎮","storage":"1","varName":"unmute","name":"Find Role"},{"member":"0","varName2":"","role":"3","varName":"unmute","name":"Remove Member Role"},{"channel":"0","varName":"","message":"${mentionedUser} Został wyciszony przez ${member}","storage":"0","varName2":"","name":"Send Message"}]},{"name":"unmute","permissions":"MUTE_MEMBERS","restriction":"1","actions":[{"info":"1","find":"🔇Wyciszony🔇","storage":"1","varName":"mute","name":"Find Role"},{"member":"0","varName2":"","role":"3","varName":"mute","name":"Remove Member Role"},{"info":"1","find":"🎮Gracz🎮","storage":"1","varName":"unmute","name":"Find Role"},{"member":"0","varName2":"","role":"3","varName":"unmute","name":"Add Member Role"},{"channel":"0","varName":"","message":"${mentionedUser} Został odciszony przez ${member}","storage":"0","varName2":"","name":"Send Message"}]}]